eldar_textformatter_matrix-0.1.0.dist-info/licenses/LICENSE
textformatter/__init__.py
textformatter/formatter.py
eldar_textformatter_matrix-0.1.0.dist-info/METADATA
eldar_textformatter_matrix-0.1.0.dist-info/WHEEL
eldar_textformatter_matrix-0.1.0.dist-info/top_level.txt
eldar_textformatter_matrix-0.1.0.dist-info/RECORD
